LICENSE.txt
MANIFEST.in
README.md
setup.py
humilis_firehose/__init__.py
humilis_firehose/meta.yaml.j2
humilis_firehose/outputs.yaml.j2
humilis_firehose/plugin.py
humilis_firehose/resources.yaml.j2
humilis_firehose.egg-info/PKG-INFO
humilis_firehose.egg-info/SOURCES.txt
humilis_firehose.egg-info/dependency_links.txt
humilis_firehose.egg-info/entry_points.txt
humilis_firehose.egg-info/not-zip-safe
humilis_firehose.egg-info/requires.txt
humilis_firehose.egg-info/top_level.txt