Metadata-Version: 2.1
Name: humilis-firehose
Version: 0.3.0
Summary: Humilis plug-in to create Firehose delivery streams
Home-page: https://github.com/humilis/humilis-firehose
Author: German Gomez-Herrero, FindHotel BV
Author-email: german@findhotel.net
License: MIT
Platform: UNKNOWN
Classifier: Programming Language :: Python :: 3
License-File: LICENSE.txt
